{
 "shapes": [
  {
   "points": [
    [
     26,
     503
    ],
    [
     355,
     569
    ]
   ],
   "label": "edit_string"
  },
  {
   "points": [
    [
     9,
     422
    ],
    [
     355,
     470
    ]
   ],
   "label": "privacy"
  },
  {
   "points": [
    [
     178,
     386
    ],
    [
     203,
     398
    ]
   ],
   "label": "number"
  },
  {
   "points": [
    [
     80,
     381
    ],
    [
     113,
     398
    ]
   ],
   "label": "other"
  },
  {
   "points": [
    [
     319,
     368
    ],
    [
     349,
     380
    ]
   ],
   "label": "other"
  },
  {
   "points": [
    [
     296,
     368
    ],
    [
     310,
     380
    ]
   ],
   "label": "edit_string"
  },
  {
   "points": [
    [
     212,
     368
    ],
    [
     293,
     398
    ]
   ],
   "label": "other"
  },
  {
   "points": [
    [
     133,
     368
    ],
    [
     161,
     389
    ]
   ],
   "label": "other"
  },
  {
   "points": [
    [
     122,
     368
    ],
    [
     130,
     389
    ]
   ],
   "label": "heart_icon"
  },
  {
   "points": [
    [
     33,
     368
    ],
    [
     79,
     398
    ]
   ],
   "label": "other"
  },
  {
   "points": [
    [
     9,
     368
    ],
    [
     37,
     398
    ]
   ],
   "label": "edit_string"
  },
  {
   "points": [
    [
     305,
     197
    ],
    [
     324,
     204
    ]
   ],
   "label": "top_bar"
  },
  {
   "points": [
    [
     9,
     197
    ],
    [
     360,
     317
    ]
   ],
   "label": "edit_string"
  },
  {
   "points": [
    [
     347,
     183
    ],
    [
     355,
     191
    ]
   ],
   "label": "other"
  },
  {
   "points": [
    [
     195,
     179
    ],
    [
     265,
     204
    ]
   ],
   "label": "other"
  },
  {
   "points": [
    [
     178,
     179
    ],
    [
     203,
     191
    ]
   ],
   "label": "rating"
  },
  {
   "points": [
    [
     105,
     170
    ],
    [
     152,
     204
    ]
   ],
   "label": "other"
  },
  {
   "points": [
    [
     247,
     161
    ],
    [
     276,
     164
    ]
   ],
   "label": "box"
  },
  {
   "points": [
    [
     220,
     161
    ],
    [
     237,
     164
    ]
   ],
   "label": "box"
  },
  {
   "points": [
    [
     268,
     152
    ],
    [
     355,
     204
    ]
   ],
   "label": "other"
  },
  {
   "points": [
    [
     127,
     144
    ],
    [
     208,
     168
    ]
   ],
   "label": "cart_add"
  },
  {
   "points": [
    [
     257,
     138
    ],
    [
     265,
     152
    ]
   ],
   "label": "box"
  },
  {
   "points": [
    [
     341,
     134
    ],
    [
     349,
     141
    ]
   ],
   "label": "cart_add"
  },
  {
   "points": [
    [
     285,
     134
    ],
    [
     296,
     146
    ]
   ],
   "label": "check"
  },
  {
   "points": [
    [
     217,
     129
    ],
    [
     239,
     154
    ]
   ],
   "label": "box"
  },
  {
   "points": [
    [
     9,
     75
    ],
    [
     355,
     137
    ]
   ],
   "label": "edit_string"
  },
  {
   "points": [
    [
     181,
     0
    ],
    [
     208,
     4
    ]
   ],
   "label": "cart_add"
  },
  {
   "points": [
    [
     9,
     0
    ],
    [
     355,
     47
    ]
   ],
   "label": "edit_string"
  }
 ],
 "imageHeight": 567,
 "imageWidth": 360,
 "flags": {
  ".": true
 }
}