{
 "shapes": [
  {
   "points": [
    [
     223,
     548
    ],
    [
     248,
     551
    ]
   ],
   "label": "number"
  },
  {
   "points": [
    [
     206,
     498
    ],
    [
     310,
     515
    ]
   ],
   "label": "filter"
  },
  {
   "points": [
    [
     26,
     494
    ],
    [
     130,
     515
    ]
   ],
   "label": "filter"
  },
  {
   "points": [
    [
     26,
     449
    ],
    [
     62,
     461
    ]
   ],
   "label": "filter"
  },
  {
   "points": [
    [
     15,
     377
    ],
    [
     130,
     416
    ]
   ],
   "label": "name"
  },
  {
   "points": [
    [
     9,
     0
    ],
    [
     360,
     267
    ]
   ],
   "label": "image"
  }
 ],
 "imageHeight": 567,
 "imageWidth": 360,
 "flags": {
  ".": true
 }
}